dsmpy/__init__.py
dsmpy/_tipsv.py
dsmpy/_tish.py
dsmpy/component.py
dsmpy/dataset.py
dsmpy/definitions.py
dsmpy/dsm.py
dsmpy/event.py
dsmpy/main.py
dsmpy/modelparameters.py
dsmpy/seismicmodel.py
dsmpy/station.py
dsmpy/window.py
dsmpy/windowmaker.py
dsmpy/flib/tipsv.cpython-37m-darwin.so
dsmpy/flib/tish.cpython-37m-darwin.so
dsmpy/flib/tipsv.cpython-37m-darwin.so.dSYM/Contents/Info.plist
dsmpy/flib/tipsv.cpython-37m-darwin.so.dSYM/Contents/Resources/DWARF/tipsv.cpython-37m-darwin.so
dsmpy/flib/tish.cpython-37m-darwin.so.dSYM/Contents/Info.plist
dsmpy/flib/tish.cpython-37m-darwin.so.dSYM/Contents/Resources/DWARF/tish.cpython-37m-darwin.so
dsmpy/resources/__init__.py
dsmpy/resources/scardec.pkl
dsmpy/spc/__init__.py
dsmpy/spc/spctime.py
dsmpy/spc/stf.py
dsmpy/spc/stfcatalog.py
dsmpy/utils/__init__.py
dsmpy/utils/cmtcatalog.py
dsmpy/utils/scardec.py
dsmpy-1.0a2.dist-info/LICENSE.txt
dsmpy-1.0a2.dist-info/METADATA
dsmpy-1.0a2.dist-info/WHEEL
dsmpy-1.0a2.dist-info/top_level.txt
dsmpy-1.0a2.dist-info/RECORD
