Metadata-Version: 2.1
Name: dsmpy
Version: 1.0a2
Summary: Python wrapper for DSM
Home-page: https://github.com/afeborgeaud/dsmpy
Author: Anselme Borgeaud, Kensuke Konishi
Author-email: aborgeaud@gmail.com
License: MIT
Platform: UNKNOWN
Classifier: Development Status :: 3 - Alpha
Classifier: Intended Audience :: Developers
Classifier: Programming Language :: Python :: 3
Classifier: License :: OSI Approved :: MIT License
Classifier: Operating System :: OS Independent
Requires-Python: >=3.7
Requires-Dist: obspy
Requires-Dist: mpi4py
Requires-Dist: pandas
Requires-Dist: matplotlib
Requires-Dist: geographiclib
Requires-Dist: numpy
